fmd_api/__init__.py
fmd_api/_version.py
fmd_api/client.py
fmd_api/device.py
fmd_api/exceptions.py
fmd_api/helpers.py
fmd_api/models.py
fmd_api/py.typed
fmd_api-2.0.5.dist-info/METADATA
fmd_api-2.0.5.dist-info/WHEEL
fmd_api-2.0.5.dist-info/top_level.txt
fmd_api-2.0.5.dist-info/RECORD
