Metadata-Version: 2.4
Name: fmd_api
Version: 2.0.5
Summary: A Python client for the FMD (Find My Device) server API
Author: devinslick
Project-URL: Homepage, https://github.com/devinslick/fmd_api
Project-URL: Repository, https://github.com/devinslick/fmd_api
Project-URL: Issues, https://github.com/devinslick/fmd_api/issues
Project-URL: Documentation, https://github.com/devinslick/fmd_api#readme
Keywords: fmd,find-my-device,location,tracking,device-tracking,api-client
Classifier: Programming Language :: Python :: 3
Classifier: Programming Language :: Python :: 3.8
Classifier: Programming Language :: Python :: 3.9
Classifier: Programming Language :: Python :: 3.10
Classifier: Programming Language :: Python :: 3.11
Classifier: Programming Language :: Python :: 3.12
Classifier: License :: OSI Approved :: MIT License
Classifier: Operating System :: OS Independent
Classifier: Development Status :: 4 - Beta
Classifier: Intended Audience :: Developers
Classifier: Topic :: Software Development :: Libraries :: Python Modules
Classifier: Topic :: System :: Monitoring
Requires-Python: >=3.8
Requires-Dist: argon2-cffi
Requires-Dist: cryptography
Requires-Dist: aiohttp
Provides-Extra: dev
Requires-Dist: pytest>=7.0; extra == "dev"
Requires-Dist: pytest-asyncio; extra == "dev"
Requires-Dist: pytest-cov; extra == "dev"
Requires-Dist: aioresponses>=0.7.0; extra == "dev"
Requires-Dist: black; extra == "dev"
Requires-Dist: flake8; extra == "dev"
Requires-Dist: mypy; extra == "dev"
Requires-Dist: pre-commit; extra == "dev"
